mathinterpreter/__init__.py
mathinterpreter/__main__.py
mathinterpreter/calculate.py
mathinterpreter/interpreter.py
mathinterpreter/lexer.py
mathinterpreter/nodes.py
mathinterpreter/parser.py
mathinterpreter/tokens.py
mathinterpreter/values.py
mathinterpreter-0.2.1a0.dist-info/LICENSE
mathinterpreter-0.2.1a0.dist-info/METADATA
mathinterpreter-0.2.1a0.dist-info/WHEEL
mathinterpreter-0.2.1a0.dist-info/entry_points.txt
mathinterpreter-0.2.1a0.dist-info/top_level.txt
mathinterpreter-0.2.1a0.dist-info/RECORD
