Metadata-Version: 2.1
Name: mathinterpreter
Version: 0.2.1a0
Summary: An interpreter for evaluating simple math expressions.
Author: Marco Barbosa, Henrique Guidi, David Callanan
Maintainer: Marco Barbosa, Henrique Guidi
License: MIT License
Project-URL: repository, https://github.com/ScientificThought/mathinterpreter
Keywords: calculator,interpreter,math
Classifier: Development Status :: 4 - Beta
Classifier: Environment :: Console
Classifier: Intended Audience :: Developers
Classifier: Intended Audience :: Education
Classifier: Intended Audience :: End Users/Desktop
Classifier: License :: OSI Approved :: MIT License
Classifier: Natural Language :: English
Classifier: Operating System :: OS Independent
Classifier: Topic :: Scientific/Engineering :: Mathematics
Classifier: Topic :: Software Development :: Interpreters
Requires-Python: >=3.10
License-File: LICENSE
Provides-Extra: dev
Requires-Dist: pytest >=8.0 ; extra == 'dev'
Requires-Dist: coverage >=7.0 ; extra == 'dev'
Requires-Dist: black >=24.0 ; extra == 'dev'
